docker_gha_runner/__init__.py
docker_gha_runner/cli.py
docker_gha_runner/const.py
docker_gha_runner/main.py
docker_gha_runner/types/__init__.py
docker_gha_runner/types/container_info.py
docker_gha_runner/types/docker_container_status.py
docker_gha_runner/types/docker_gha_runner_config/__init__.py
docker_gha_runner/types/docker_gha_runner_config/docker.py
docker_gha_runner/types/docker_gha_runner_config/github.py
docker_gha_runner/types/docker_gha_runner_config/main.py
docker_gha_runner/types/docker_gha_runner_config/runner.py
docker_gha_runner/types/gh_entity.py
docker_gha_runner/types/runner_status.py
docker_gha_runner/util/__init__.py
docker_gha_runner/util/api/__init__.py
docker_gha_runner/util/api/docker.py
docker_gha_runner/util/api/github.py
docker_gha_runner/util/dict2liststr.py
docker_gha_runner/version.py
docker_gha_runner-0.1.3.dist-info/METADATA
docker_gha_runner-0.1.3.dist-info/WHEEL
docker_gha_runner-0.1.3.dist-info/entry_points.txt
docker_gha_runner-0.1.3.dist-info/RECORD
