Metadata-Version: 2.1
Name: docker_gha_runner
Version: 0.1.3
Summary: GitHub Action Self-hosted Runner Operator for Docker
Author: Kyosuke Miyamura
Author-email: ask@386.jp
Requires-Python: >=3.11,<4.0
Classifier: Programming Language :: Python :: 3
Classifier: Programming Language :: Python :: 3.11
Classifier: Programming Language :: Python :: 3.12
Requires-Dist: cryptography (>=42.0.5,<43.0.0)
Requires-Dist: docker (>=7.0.0,<8.0.0)
Requires-Dist: jwt (>=1.3.1,<2.0.0)
Requires-Dist: pydantic (>=2.6.4,<3.0.0)
Requires-Dist: python-dotenv (>=1.0.1,<2.0.0)
Requires-Dist: pyyaml (>=6.0.1,<7.0.0)
Requires-Dist: requests (>=2.31.0,<3.0.0)
